lindle/__init__.py
lindle-1.0.0.dist-info/LICENSE
lindle-1.0.0.dist-info/METADATA
lindle-1.0.0.dist-info/WHEEL
lindle-1.0.0.dist-info/top_level.txt
lindle-1.0.0.dist-info/RECORD
