Metadata-Version: 2.1
Name: lindle
Version: 1.0.0
Summary: Lindle Python API saving tool to keep all your links all in one place
Home-page: https://lindle.me
Author: M2K Developments
Author-email: m2kdevelopments@gmail.com
License: MIT
Keywords: lindle links bookmarks
Classifier: Programming Language :: Python :: 3
Classifier: License :: OSI Approved :: MIT License
Classifier: Operating System :: OS Independent
Requires-Python: >=3.6
License-File: LICENSE
